[
  {
    "uid": "55214751-9931-41c6-abf2-35181d90ad4f",
    "time": 3.877744,
    "location": {
      "x": -53.7400055,
      "y": 0.0202000141,
      "z": -40.411
    },
    "content": "Hey Gloria, can you check out my latest Instagram post? I need your honest opinion.",
    "speaker": "Chloe Wilson"
  },
  {
    "uid": "a947cc61-91bb-44d6-9fcb-de1a2e29c09f",
    "time": 4.06676245,
    "location": {
      "x": -54.833,
      "y": 0.0202000141,
      "z": -35.48
    },
    "content": "Hey Alex, how's your project coming along? Need any tips?",
    "speaker": "Lisa Patel"
  },
  {
    "uid": "5d22569a-17d6-4b19-89f9-4c0e261a2bc9",
    "time": 4.1097846,
    "location": {
      "x": -55.427002,
      "y": 0.0202000141,
      "z": -50.027
    },
    "content": "Hey Karen, what's going on? You ready for the game later?",
    "speaker": "Jason Miller"
  },
  {
    "uid": "ccd23f2a-b93b-4800-b950-4917442c34e9",
    "time": 4.253595,
    "location": {
      "x": -31.684,
      "y": 0.0202000141,
      "z": -52.49
    },
    "content": "Hey Audrey, you good? You look like you’ve got something on your mind.",
    "speaker": "William Davis"
  },
  {
    "uid": "4e4dc492-1d0f-46ac-b4de-878c5c726095",
    "time": 4.281155,
    "location": {
      "x": -5.745173,
      "y": 0.0202000141,
      "z": -40.62813
    },
    "content": "Hey everyone, I wanted to get your thoughts on the agenda for the next student council meeting.",
    "speaker": "Ethan Wilson"
  },
  {
    "uid": "99b7fc7d-d389-476e-a69b-4e7988be6dab",
    "time": 4.33162642,
    "location": {
      "x": -73.20901,
      "y": 0.0202000141,
      "z": -35.469
    },
    "content": "Hey Helen, what's going on? Ready for the next class?",
    "speaker": "Lucas Wilson"
  },
  {
    "uid": "bd392f7d-f2bb-4ded-833b-5374cd27c36f",
    "time": 4.36218929,
    "location": {
      "x": -14.04851,
      "y": 0.0202000141,
      "z": -28.852
    },
    "content": "Hi Jordan, how's everything going with the lunch setup?",
    "speaker": "Diane Jackson"
  },
  {
    "uid": "8e7eee08-c13e-4862-bac1-9044d8d790a6",
    "time": 4.4448266,
    "location": {
      "x": -4.89091158,
      "y": 0.0202000141,
      "z": -30.4604244
    },
    "content": "Hey Benjamin and James, did you hear about the new exoplanet they discovered?",
    "speaker": "Jackson Davis"
  },
  {
    "uid": "39227451-eed8-4e44-884b-7ccb0db9dc85",
    "time": 4.45982838,
    "location": {
      "x": -12.203,
      "y": 0.0202000141,
      "z": -43.1025658
    },
    "content": "Hey Olivia, Daniel, how are your coding projects coming along?",
    "speaker": "Thomas Wright"
  },
  {
    "uid": "44df20b4-2166-43a7-ac86-92f23ca01d58",
    "time": 4.61579466,
    "location": {
      "x": -12.301,
      "y": 0.0202000141,
      "z": -37.89657
    },
    "content": "Hey Isabella, you got a minute to talk about the game plan?",
    "speaker": "Sebastian Garcia"
  },
  {
    "uid": "b033b8f0-8191-4ac7-b99b-054dc029ae9c",
    "time": 4.64295864,
    "location": {
      "x": -11.0224094,
      "y": 0.0202000141,
      "z": -30.3448868
    },
    "content": "Hey Emma, Caleb, I’ve been working on a new beat. Would you guys be down to add some vocals or ideas?",
    "speaker": "Lucas Garcia"
  },
  {
    "uid": "ecc5071d-df68-4ae5-9d54-fa70171f43ef",
    "time": 4.736277,
    "location": {
      "x": -74.883,
      "y": 0.0202000141,
      "z": -36.915
    },
    "content": "Good morning, everyone. How are you all feeling today?",
    "speaker": "Helen Martinez"
  },
  {
    "uid": "90d094bd-f123-431b-861d-a5252432c36c",
    "time": 4.753758,
    "location": {
      "x": -8.723,
      "y": 0.0202000141,
      "z": -28.883
    },
    "content": "Hey Lucas, what's up? Heard anything interesting lately?",
    "speaker": "Emma Taylor"
  },
  {
    "uid": "4075efab-0d01-41e0-aa5f-35d04e829176",
    "time": 4.808443,
    "location": {
      "x": -5.00152731,
      "y": 0.07019997,
      "z": -32.88103
    },
    "content": "Madison, do you have a moment to discuss the debate topics?",
    "speaker": "Benjamin Moore"
  },
  {
    "uid": "a976ba6c-d3f2-4e1a-b59a-8ce66c1f4c69",
    "time": 4.85023737,
    "location": {
      "x": -45.9090042,
      "y": 0.0202000141,
      "z": -53.118
    },
    "content": "Hey Amelia, do you have a moment to talk about music?",
    "speaker": "Mia Rodriguez"
  },
  {
    "uid": "f85ae982-eed8-4eed-bcfe-d67efa4d739d",
    "time": 4.912559,
    "location": {
      "x": -4.890855,
      "y": 0.0202000141,
      "z": -27.93171
    },
    "content": "Hey Jackson, Henry, let's talk about the game plan for Friday. We need to be ready to dominate the court.",
    "speaker": "James Rodriguez"
  },
  {
    "uid": "c4371fb4-89f0-4b5e-9a58-74d3a394f697",
    "time": 4.940043,
    "location": {
      "x": -43.5230026,
      "y": 0.0202000141,
      "z": -51.652
    },
    "content": "Hey Natalie, Mia, do you need any help with the assignment?",
    "speaker": "Amelia Chen"
  },
  {
    "uid": "6c03610f-b1be-4f19-93b4-077b9218c7cf",
    "time": 4.957165,
    "location": {
      "x": -8.610039,
      "y": 0.0202000141,
      "z": -40.3041077
    },
    "content": "Hey Olivia, Ethan, how's it going? Ready for the game this Friday?",
    "speaker": "Jackson Lee"
  },
  {
    "uid": "1ccce890-63de-4806-968b-674d7add402e",
    "time": 4.957165,
    "location": {
      "x": -10.9928951,
      "y": 0.0202000141,
      "z": -32.8831253
    },
    "content": "Hey Isabella, Lucas, do you have a minute? I want to run an app idea by you.",
    "speaker": "Caleb Wright"
  },
  {
    "uid": "8cfac2b3-8103-4c0e-b1b9-8be8f09ff489",
    "time": 4.9723115,
    "location": {
      "x": -51.2820053,
      "y": 0.0202000141,
      "z": -35.469
    },
    "content": "Hey Alex, did you hear about the math book that got arrested? It had too many problems!",
    "speaker": "Ethan Brown"
  },
  {
    "uid": "7b904b10-ee74-4090-8ae3-3afc80c7a3a0",
    "time": 5.036681,
    "location": {
      "x": -64.73399,
      "y": 0.0202000141,
      "z": -40.411
    },
    "content": "Hey Ava, did you get a chance to look at the data from our last experiment?",
    "speaker": "Evelyn Martinez"
  },
  {
    "uid": "d640bd56-cc41-4352-aa28-d6f33510e542",
    "time": 5.06914473,
    "location": {
      "x": -32.036,
      "y": 0.0202000141,
      "z": -26.111
    },
    "content": "Hey Benjamin, how’s your photography project coming along?",
    "speaker": "Charlotte Davis"
  },
  {
    "uid": "08beacf5-3e81-420f-990d-91257080383e",
    "time": 5.1250267,
    "location": {
      "x": -44.497,
      "y": 0.0202000141,
      "z": -50.027
    },
    "content": "Hey Amelia, how are you feeling after practice yesterday?",
    "speaker": "Natalie Chen"
  },
  {
    "uid": "ca39fcbb-77df-471f-a5ce-dcbfafa837f4",
    "time": 5.19131041,
    "location": {
      "x": -52.956,
      "y": 0.0202000141,
      "z": -36.915
    },
    "content": "Hey Lisa, have you seen any thought-provoking art lately? I'm looking for some inspiration.",
    "speaker": "Alex Rivera"
  },
  {
    "uid": "842a8b68-f4df-47c8-8c8e-7253de2794a3",
    "time": 5.206932,
    "location": {
      "x": -6.17395163,
      "y": 0.07019997,
      "z": -37.8751678
    },
    "content": "Hi Madison, how are you doing today? I was thinking about starting a discussion on cultural diversity in our club next week.",
    "speaker": "Zainab Malik"
  },
  {
    "uid": "18586ebc-a72a-4db8-bf2f-2be9bde34486",
    "time": 5.206932,
    "location": {
      "x": -5.02624846,
      "y": 0.0202000141,
      "z": -35.39085
    },
    "content": "Hey Zainab, do you want to form a study group for the exams?",
    "speaker": "Madison Lee"
  },
  {
    "uid": "ccffb518-81dc-4442-bbd0-104eb27471a9",
    "time": 5.22530556,
    "location": {
      "x": -65.8269958,
      "y": 0.0202000141,
      "z": -35.48
    },
    "content": "Hey Elijah, why don’t skeletons fight each other? Because they don’t have the guts!",
    "speaker": "Matthew Brown"
  },
  {
    "uid": "40451d83-acb2-4c1d-a356-088bedaed19c",
    "time": 5.24098635,
    "location": {
      "x": -62.276,
      "y": 0.0202000141,
      "z": -35.469
    },
    "content": "Elijah, how's the essay coming along? Need any help?",
    "speaker": "Sarah Johnson"
  },
  {
    "uid": "0902db6e-b60a-4a1e-8308-3aaf4a89f3ff",
    "time": 5.25670862,
    "location": {
      "x": -31.969,
      "y": 0.0202000141,
      "z": -24.876
    },
    "content": "Charlotte, do you ever think about how fleeting our existence is in the grand scheme of things?",
    "speaker": "Benjamin Scott"
  },
  {
    "uid": "be14608b-6ba1-41b1-9c38-f3a4a736ffb5",
    "time": 5.25670862,
    "location": {
      "x": -6.19922256,
      "y": 0.0202000141,
      "z": -35.4520226
    },
    "content": "Hey Zainab, Madison, Benjamin! How's everyone doing today?",
    "speaker": "Amelia Robinson"
  },
  {
    "uid": "4f62b076-d331-466b-b493-a762dd02a502",
    "time": 5.361577,
    "location": {
      "x": -30.884,
      "y": 0.0202000141,
      "z": -43.434
    },
    "content": "Hi Aiden, I really liked your painting from last week. Do you have any tips for blending colors?",
    "speaker": "Emily Zhang"
  },
  {
    "uid": "573969a0-4a92-47d0-bcf4-d874cd563fe0",
    "time": 5.379286,
    "location": {
      "x": -24.357,
      "y": 0.0202000141,
      "z": -29.393
    },
    "content": "Good afternoon, Zoe. Are you looking for something specific or just enjoying the garden?",
    "speaker": "Walter Thompson"
  },
  {
    "uid": "333bf283-c422-4a8f-b152-a6d85cf26b95",
    "time": 5.40027046,
    "location": {
      "x": -51.439003,
      "y": 0.0202000141,
      "z": -38.535
    },
    "content": "Alex, Chloe, how are you two doing? Ready for lunch?",
    "speaker": "Gloria Washington"
  },
  {
    "uid": "c8423dbc-05b0-47b5-8fb5-245f079725d7",
    "time": 5.510659,
    "location": {
      "x": -11.1077766,
      "y": 0.0202000141,
      "z": -37.9231339
    },
    "content": "Hey Olivia, do you have a moment? I’d love to hear your thoughts for the yearbook.",
    "speaker": "Victoria Wright"
  },
  {
    "uid": "938b9102-5321-41d7-9e59-0ebd3d994f1a",
    "time": 5.58764029,
    "location": {
      "x": -4.021808,
      "y": 0.0202000141,
      "z": -38.96315
    },
    "content": "Hey everyone, have you heard about the environmental awareness campaign we're planning? It's going to be a big event!",
    "speaker": "Harper Garcia"
  },
  {
    "uid": "8844ade5-515c-4d64-b402-fd59f80acfd6",
    "time": 5.603714,
    "location": {
      "x": -12.405,
      "y": 0.0202000141,
      "z": -35.3735657
    },
    "content": "Hey Victoria! I’ve been thinking about our project—let’s brainstorm some ideas!",
    "speaker": "Isabella Lopez"
  },
  {
    "uid": "8f6b51e8-56f1-4e78-9b71-ec03b396ba95",
    "time": 6.629287,
    "location": {
      "x": -48.192,
      "y": 0.0202000141,
      "z": -50.599
    },
    "content": "Hey Marcus! Are you going to the talent show next week? I’m thinking of performing a new song!",
    "speaker": "Sophia Garcia"
  },
  {
    "uid": "b2419464-ca86-4743-87a5-9fc83ea7831f",
    "time": 10.9414816,
    "location": {
      "x": -31.5619583,
      "y": 0.0101999044,
      "z": -51.947773
    },
    "content": "Seriously, Audrey, if something’s bothering you, you can talk to me. I’ve got your back.",
    "speaker": "William Davis"
  },
  {
    "uid": "d928299a-9366-46bd-ba2f-21e36b7114ba",
    "time": 11.4019661,
    "location": {
      "x": -30.376915,
      "y": 0.0101999044,
      "z": -43.92181
    },
    "content": "I’ve been struggling with getting the colors to blend smoothly. Do you use a specific technique?",
    "speaker": "Emily Zhang"
  },
  {
    "uid": "f4c96ff4-d433-4c1d-9ca7-27454cd83fcd",
    "time": 11.9893875,
    "location": {
      "x": -54.56266,
      "y": 0.0101999044,
      "z": -51.2252655
    },
    "content": "Mason! You ready to crush it later? We’re gonna dominate!",
    "speaker": "Jason Miller"
  },
  {
    "uid": "bb06010b-bf21-4a67-89f3-4c800290e433",
    "time": 12.2405434,
    "location": {
      "x": -54.4519577,
      "y": 0.0101999044,
      "z": -51.8149643
    },
    "content": "¡Hola, Jason y Mason! ¿Cómo están hoy?",
    "speaker": "Karen Martinez"
  },
  {
    "uid": "0831c18c-e04f-4fa2-bb35-a059a104be67",
    "time": 12.5308361,
    "location": {
      "x": -10.9982557,
      "y": 0.0101999044,
      "z": -40.9902649
    },
    "content": "Jackson, Ethan, how are your coding projects progressing?",
    "speaker": "Thomas Wright"
  },
  {
    "uid": "0720c7fe-9a02-4c20-b6b9-a5a150ae2f5b",
    "time": 12.596817,
    "location": {
      "x": -5.02458,
      "y": 0.17019999,
      "z": -25.405735
    },
    "content": "Hey James, any news on the robotics competition?",
    "speaker": "Henry Johnson"
  },
  {
    "uid": "d513f8b3-2047-4959-a01b-787552218b38",
    "time": 12.8801985,
    "location": {
      "x": -71.04942,
      "y": 0.0151999,
      "z": -42.9823341
    },
    "content": "Hey Olivia! ¿Cómo estás?",
    "speaker": "Mateo Diaz"
  },
  {
    "uid": "1e4fbbe6-d5c6-4015-8497-c3ff4d40ac79",
    "time": 12.9742327,
    "location": {
      "x": -31.7958412,
      "y": 0.0202000141,
      "z": -51.2259
    },
    "content": "Hey William, do you have a moment to talk about art?",
    "speaker": "Audrey Thompson"
  },
  {
    "uid": "3027d596-475e-4518-b2d2-1c34caa8c53a",
    "time": 13.0976276,
    "location": {
      "x": -10.80594,
      "y": 0.07019997,
      "z": -25.3887482
    },
    "content": "Hey Aiden! How's it going?",
    "speaker": "Harper Wilson"
  },
  {
    "uid": "39cb3339-be4a-4d2d-9524-5d63d7d424b3",
    "time": 13.3694115,
    "location": {
      "x": -25.9176521,
      "y": 0.0101999044,
      "z": -29.3487854
    },
    "content": "Hey Walter, do you have a minute? I wanted to discuss something important.",
    "speaker": "Zoe Miller"
  },
  {
    "uid": "ca05c1f9-b8e9-40cd-a18a-5dbee59f0b61",
    "time": 13.4387712,
    "location": {
      "x": -51.15825,
      "y": 0.0202000141,
      "z": -50.1502342
    },
    "content": "Hey Sophia, how's everything going today?",
    "speaker": "Marcus Johnson"
  },
  {
    "uid": "30c716bf-4db0-490f-9636-df98d20045f2",
    "time": 13.4681,
    "location": {
      "x": -76.41254,
      "y": 0.0101999044,
      "z": -35.7622681
    },
    "content": "Lucas, how are you feeling today? Any headaches or anything bothering you?",
    "speaker": "Helen Martinez"
  },
  {
    "uid": "4220b52c-539c-4804-a30e-5b55e1c0ef81",
    "time": 13.609827,
    "location": {
      "x": -62.45125,
      "y": 0.0202000141,
      "z": -38.3994522
    },
    "content": "Hey guys, I’ve been working on a monologue for my audition. Mind if I run it by you?",
    "speaker": "Ava Martinez"
  },
  {
    "uid": "6587cf40-a451-4197-88f3-509668d14147",
    "time": 13.9552279,
    "location": {
      "x": -3.26698875,
      "y": 0.0202000141,
      "z": -39.0713
    },
    "content": "Hey Harper, have you thought about the new debate topic? I’d love to hear your take on it.",
    "speaker": "Scarlett Kim"
  },
  {
    "uid": "c680886e-f497-43f8-9364-d4eb94755848",
    "time": 13.9698,
    "location": {
      "x": -52.92492,
      "y": 0.0101999044,
      "z": -36.67456
    },
    "content": "Hey Gloria, did you know Lisa’s backpack is secretly a time machine? She’s always late because she’s traveling through the 90s!",
    "speaker": "Ethan Brown"
  },
  {
    "uid": "3f6187d3-7274-4f8e-b9de-c608073d8e70",
    "time": 14.0216684,
    "location": {
      "x": -73.3660049,
      "y": 0.0202000141,
      "z": -38.535
    },
    "content": "Alright, Tyler, Helen, let's get some energy going! Who's up for a quick jog to the gym?",
    "speaker": "David Thompson"
  },
  {
    "uid": "83fddf4f-18fe-44a7-b69a-ffecc6958882",
    "time": 14.0392084,
    "location": {
      "x": -67.898,
      "y": 0.0202000141,
      "z": -53.118
    },
    "content": "Hey Noah, what are you working on? It looks interesting.",
    "speaker": "Elizabeth Wilson"
  },
  {
    "uid": "9ac6fa0d-8a5d-4380-888c-1b3935bb02c3",
    "time": 14.0392084,
    "location": {
      "x": -56.8389969,
      "y": 0.0202000141,
      "z": -53.118
    },
    "content": "Hey Karen, you ready for the tryouts next week? I’ve been practicing my three-pointers like crazy.",
    "speaker": "Mason Scott"
  },
  {
    "uid": "2a4a0521-a4fc-4da3-84fc-e48055300413",
    "time": 14.0688286,
    "location": {
      "x": -12.204361,
      "y": 0.0101999044,
      "z": -25.45644
    },
    "content": "Hey Harper, have you checked out the new AI framework I mentioned last week?",
    "speaker": "Aiden Thompson"
  },
  {
    "uid": "b75d6c0a-da00-4ed9-bbc0-92e35cf946ff",
    "time": 14.3906517,
    "location": {
      "x": -6.60846663,
      "y": 0.0101999044,
      "z": -37.78351
    },
    "content": "Hey Harper, would you be interested in forming a study group for the exams?",
    "speaker": "Madison Lee"
  },
  {
    "uid": "056dcec0-e4d9-43e9-9911-9f02959e77bd",
    "time": 14.4318933,
    "location": {
      "x": -66.486,
      "y": 0.0202000141,
      "z": -50.027
    },
    "content": "Hey Noah, how's your ankle feeling today?",
    "speaker": "Emma Rodriguez"
  },
  {
    "uid": "134600b7-469a-49e4-928d-1d84a1ec84ae",
    "time": 14.4318933,
    "location": {
      "x": -5.02624846,
      "y": 0.0101999044,
      "z": -35.39085
    },
    "content": "Amelia, we're talking about cultural diversity for the club next week. Would you like to join the discussion?",
    "speaker": "Zainab Malik"
  },
  {
    "uid": "4a6fb851-c8a4-4ff5-a1f4-79344ef82805",
    "time": 14.47595,
    "location": {
      "x": -5.721887,
      "y": 0.0202000141,
      "z": -43.0507774
    },
    "content": "Hey Ethan, you good? You look like you've got something on your mind.",
    "speaker": "Noah Johnson"
  },
  {
    "uid": "9d2a07df-680e-447c-868f-993c2cd3a500",
    "time": 14.9035292,
    "location": {
      "x": -59.166,
      "y": 0.0202000141,
      "z": -37.315
    },
    "content": "Alright, time to gather some supplies!",
    "speaker": "Jennifer Lee"
  },
  {
    "uid": "41deb05e-65d8-4035-8302-c2c81be657d3",
    "time": 15.4884119,
    "location": {
      "x": -63.81629,
      "y": 0.0202000141,
      "z": -37.0044632
    },
    "content": "Hey Matt, you heard about the new skatepark they’re putting up?",
    "speaker": "Elijah Thompson"
  },
  {
    "uid": "2830a367-63e0-4c60-b51e-e4ee94dbff19",
    "time": 15.5127935,
    "location": {
      "x": -43.4716949,
      "y": 0.0101999044,
      "z": -52.33343
    },
    "content": "Actually, I’ve been working on a new song. Would you both like to hear it?",
    "speaker": "Mia Rodriguez"
  },
  {
    "uid": "efc53c20-072d-4291-879b-7053156686eb",
    "time": 15.7884779,
    "location": {
      "x": -32.036,
      "y": 0.0101999044,
      "z": -26.111
    },
    "content": "It’s going well. I’ve been focusing on capturing the impermanence of things—like how light changes throughout the day.",
    "speaker": "Benjamin Scott"
  },
  {
    "uid": "9883acae-1c66-4a9b-9b26-2b8ad160715c",
    "time": 15.9247475,
    "location": {
      "x": -4.890902,
      "y": 0.0151999,
      "z": -30.4592686
    },
    "content": "Jackson, Benjamin, let's stick together and follow the others! We need to get out of here!",
    "speaker": "James Rodriguez"
  },
  {
    "uid": "4e3f0039-4513-43a7-8d5c-7a548c739cd2",
    "time": 15.940382,
    "location": {
      "x": -31.7484684,
      "y": 0.0151999,
      "z": -25.1135731
    },
    "content": "I think about it a lot. That’s why I love art—it’s like trying to hold onto those fleeting moments, even if just for a little while.",
    "speaker": "Charlotte Davis"
  },
  {
    "uid": "6584209c-1294-49f3-a83f-dc3b82aaf797",
    "time": 16.3612213,
    "location": {
      "x": -31.5611362,
      "y": 0.0101999044,
      "z": -51.95034
    },
    "content": "Audrey, stay down. We need to hide right now.",
    "speaker": "William Davis"
  },
  {
    "uid": "ffe370f0-9d43-4cfe-bf05-d66fc0446fbd",
    "time": 17.0532379,
    "location": {
      "x": -4.13904428,
      "y": 0.0101999044,
      "z": -38.9018
    },
    "content": "Everyone, let's stick together and move to the hallway!",
    "speaker": "Harper Garcia"
  },
  {
    "uid": "12a48d33-d4d9-4b43-a7cf-3773ea13bea3",
    "time": 17.86968,
    "location": {
      "x": -62.35814,
      "y": 0.0101999044,
      "z": -38.9921837
    },
    "content": "Elijah, have you had a chance to look at the data from our experiment? I’d love to hear your thoughts.",
    "speaker": "Evelyn Martinez"
  },
  {
    "uid": "0b27165e-3b57-44c9-8e62-6bbe5c1ed4a9",
    "time": 17.9111443,
    "location": {
      "x": -43.725563,
      "y": 0.0101999044,
      "z": -51.12109
    },
    "content": "Mia, have you noticed anything different about Amelia lately? She seemed a bit off at practice.",
    "speaker": "Natalie Chen"
  },
  {
    "uid": "1d0836a8-ed56-4d9d-b6cc-1f8439434a3e",
    "time": 18.3346119,
    "location": {
      "x": -72.90441,
      "y": 0.0101999044,
      "z": -42.7036476
    },
    "content": "Mateo, how's the solo piece coming along? We need to make sure it's performance-ready soon.",
    "speaker": "James Wilson"
  },
  {
    "uid": "761a6c44-4052-4ceb-9e05-8f33544c9e5b",
    "time": 18.3621464,
    "location": {
      "x": -64.57749,
      "y": 0.0101999044,
      "z": -36.9037781
    },
    "content": "Hey Ava, Evelyn, why did the chicken cross the road? To get to the other side... of this boring class!",
    "speaker": "Matthew Brown"
  },
  {
    "uid": "4abe8472-153d-4506-80b3-6bb3fdab138e",
    "time": 18.3621464,
    "location": {
      "x": -17.0605125,
      "y": 0.0101999044,
      "z": -17.379467
    },
    "content": "Hey Liam, have you been following the latest developments in the election? It’s like history repeating itself.",
    "speaker": "Michael Rodriguez"
  },
  {
    "uid": "c8c95f2f-60b8-4d28-8a08-1930dd3a15c9",
    "time": 18.3826,
    "location": {
      "x": -64.04918,
      "y": 0.0101999044,
      "z": -36.3930054
    },
    "content": "Matthew, that’s a good one, but let’s make sure Elijah’s essay gets the attention it deserves. Elijah, what part are you stuck on?",
    "speaker": "Sarah Johnson"
  },
  {
    "uid": "d680f7e3-1ed9-4a4c-99e3-b21d4a0b3ade",
    "time": 18.5113354,
    "location": {
      "x": -11.1550274,
      "y": 0.0101999044,
      "z": -37.91575
    },
    "content": "Jackson! Victoria and I are brainstorming for our art project—want to join us? Your photography could add such a cool dimension!",
    "speaker": "Isabella Lopez"
  },
  {
    "uid": "3489752e-dedc-4776-9f56-7c8aaa21c7e0",
    "time": 18.59822,
    "location": {
      "x": -39.10273,
      "y": 0.0101999044,
      "z": -51.60621
    },
    "content": "Sophia, stay behind me. We need to confront the shooter.",
    "speaker": "Aiden Chen"
  },
  {
    "uid": "20cdc2a0-0747-4516-b8d5-c017c6fb0ea5",
    "time": 18.61241,
    "location": {
      "x": -32.8686676,
      "y": 0.0101999044,
      "z": -49.3738251
    },
    "content": "To be, or not to be, that is the question...",
    "speaker": "Alexander Lee"
  },
  {
    "uid": "660f04a7-ff64-4943-ba43-84f69993bf0c",
    "time": 18.6552944,
    "location": {
      "x": -16.5450859,
      "y": 0.0151999,
      "z": -20.1233
    },
    "content": "Hey Michael, got a minute? I’d love to hear your thoughts on the new debate topic.",
    "speaker": "Liam Wright"
  },
  {
    "uid": "d8b8e82e-0caa-439b-a81e-34df0e01d49c",
    "time": 18.7113972,
    "location": {
      "x": -51.15825,
      "y": 0.0202000141,
      "z": -50.1502342
    },
    "content": "Sophia, stay calm and follow me to the nearest hiding spot.",
    "speaker": "Marcus Johnson"
  },
  {
    "uid": "75294d6d-85f5-4906-b6d8-1846db5d9623",
    "time": 18.9167747,
    "location": {
      "x": -72.40515,
      "y": 0.0151999,
      "z": -42.35075
    },
    "content": "Everyone, stay down and quiet! There's a shooter.",
    "speaker": "Frank Ramirez"
  },
  {
    "uid": "6c7e7bb1-801a-45db-84d8-1d74b06f9021",
    "time": 18.9996414,
    "location": {
      "x": -69.83872,
      "y": 0.0151999,
      "z": -43.7064171
    },
    "content": "¡Vamos, Olivia! We need to run to the far_right_yard!",
    "speaker": "Mateo Diaz"
  },
  {
    "uid": "20069e21-dcf0-430e-92a1-da9822e3b3c9",
    "time": 19.1847839,
    "location": {
      "x": -50.84114,
      "y": 0.0151999,
      "z": -49.8309555
    },
    "content": "Marcus, let’s go with everyone else! They’re heading to the hallway!",
    "speaker": "Sophia Garcia"
  },
  {
    "uid": "9b66abcf-5050-4753-9888-e765e03801e9",
    "time": 20.109869,
    "location": {
      "x": -25.7609425,
      "y": 0.0101999044,
      "z": -29.3267879
    },
    "content": "Walter, get down! We need to hide.",
    "speaker": "Zoe Miller"
  },
  {
    "uid": "3658afc7-c60d-4db5-bdfe-39c57da4c802",
    "time": 20.109869,
    "location": {
      "x": -4.44984341,
      "y": 0.0101999044,
      "z": -32.98773
    },
    "content": "Everyone, stay down and take cover!",
    "speaker": "Benjamin Moore"
  },
  {
    "uid": "e93594e0-c724-440d-96b8-b860b82abf8a",
    "time": 20.3257313,
    "location": {
      "x": -52.90497,
      "y": 0.0101999044,
      "z": -36.841362
    },
    "content": "Everyone, get down and stay quiet! I think there’s a shooter.",
    "speaker": "Ethan Brown"
  },
  {
    "uid": "9c5ed798-11dd-4fb7-a1b0-efd263531f4b",
    "time": 20.5279274,
    "location": {
      "x": -17.05,
      "y": 0.0101999044,
      "z": -41.0759125
    },
    "content": "Mia, we need to hide right now!",
    "speaker": "Lily Kim"
  },
  {
    "uid": "0ef153d6-9aaf-4354-8ded-d842620b3319",
    "time": 20.6054859,
    "location": {
      "x": -75.26264,
      "y": 0.0101999044,
      "z": -36.67431
    },
    "content": "Everyone, stay down and take cover! We need to stay quiet and hidden.",
    "speaker": "Helen Martinez"
  },
  {
    "uid": "06301581-6336-413f-8666-beced8d3cb4f",
    "time": 21.48665,
    "location": {
      "x": -75.429924,
      "y": 0.0101999044,
      "z": -40.04793
    },
    "content": "Tyler, let's move! Follow the others!",
    "speaker": "David Thompson"
  },
  {
    "uid": "2a1c47c6-1bcd-48be-8e22-afcc45b00e90",
    "time": 22.2021236,
    "location": {
      "x": -74.75593,
      "y": 0.0101999044,
      "z": -36.99565
    },
    "content": "Hey Jacob, David, what’s up? You guys ready for the next class?",
    "speaker": "Lucas Wilson"
  },
  {
    "uid": "f147688f-cb9d-4ea5-a169-dd0bcadda29e",
    "time": 23.0801029,
    "location": {
      "x": -65.45499,
      "y": 0.0101999044,
      "z": -51.45605
    },
    "content": "Everyone, let's stick together and move to the hallway!",
    "speaker": "Emma Rodriguez"
  },
  {
    "uid": "6de2ba0a-fa26-4d94-9b50-9f2a4d721f3d",
    "time": 23.4614372,
    "location": {
      "x": -53.4666,
      "y": 0.0101999044,
      "z": -37.05489
    },
    "content": "Actually, Alex, I recently saw an incredible exhibit blending traditional and digital art. It might give you some fresh ideas!",
    "speaker": "Lisa Patel"
  },
  {
    "uid": "19dff4c9-6e4f-41db-971f-6f68ed916083",
    "time": 23.7814064,
    "location": {
      "x": -51.0939636,
      "y": 0.0101999044,
      "z": -38.6319542
    },
    "content": "Hey Lisa, have you seen my latest Instagram post? I’d love to know what you think!",
    "speaker": "Chloe Wilson"
  },
  {
    "uid": "c7ff6786-1ca8-4de5-b4b5-36225630ebda",
    "time": 23.8743229,
    "location": {
      "x": -31.7460632,
      "y": 0.0202000141,
      "z": -51.3795547
    },
    "content": "We can't just hide! We need to do something to stop this shooter!",
    "speaker": "Audrey Thompson"
  },
  {
    "uid": "2f60488e-81bc-4c04-be3c-ac162d63d939",
    "time": 24.1165352,
    "location": {
      "x": -8.723,
      "y": 0.0101999044,
      "z": -28.883
    },
    "content": "It’s got this chill, lo-fi vibe with a hint of jazz. I think your voice would fit perfectly, Emma.",
    "speaker": "Lucas Garcia"
  },
  {
    "uid": "f4f1bd18-91ce-4e96-995c-a7d174743c27",
    "time": 24.3943787,
    "location": {
      "x": -3.94861937,
      "y": 0.0101999044,
      "z": -37.57458
    },
    "content": "Harper, that campaign sounds amazing! How can I help? Maybe we can get the cheer squad involved!",
    "speaker": "Amelia Robinson"
  },
  {
    "uid": "ca3ee682-6834-48fa-84f8-941ad082f7eb",
    "time": 24.3943787,
    "location": {
      "x": -11.0224037,
      "y": 0.0101999044,
      "z": -30.3448982
    },
    "content": "Lucas, you’re spacing out! What’s going on?",
    "speaker": "Emma Taylor"
  },
  {
    "uid": "e6b895b6-d77a-4949-8194-260edf8a8e7f",
    "time": 24.4316463,
    "location": {
      "x": -8.245243,
      "y": 0.0101999044,
      "z": -40.1566
    },
    "content": "The game’s going to be great! But before we get into that, let’s brainstorm some ideas for the student council meeting—what’s on your minds?",
    "speaker": "Ethan Wilson"
  },
  {
    "uid": "6c4224b1-7a70-4f84-8173-fb7277407deb",
    "time": 24.5035229,
    "location": {
      "x": -54.5333481,
      "y": 0.0101999044,
      "z": -36.27327
    },
    "content": "Gloria, do you think art can be a powerful tool for social change? I’d love to hear your thoughts.",
    "speaker": "Alex Rivera"
  },
  {
    "uid": "5733990f-7e77-4f74-b48c-41ef1320688c",
    "time": 24.61333,
    "location": {
      "x": -11.2143164,
      "y": 0.0101999044,
      "z": -40.64994
    },
    "content": "Everyone, get down and stay quiet. There's a shooter.",
    "speaker": "Thomas Wright"
  },
  {
    "uid": "97c7bddb-045b-4ced-918d-4b7e822a806a",
    "time": 24.9314137,
    "location": {
      "x": -64.09783,
      "y": 0.0101999044,
      "z": -36.362915
    },
    "content": "Everyone, stay calm but alert. We need to stick together and be ready to act if the shooter comes this way.",
    "speaker": "Sarah Johnson"
  },
  {
    "uid": "e781e701-f395-41f7-9934-8ae3b1d5fc44",
    "time": 25.6514568,
    "location": {
      "x": -12.6910114,
      "y": 0.0101999044,
      "z": -33.0043373
    },
    "content": "Everyone, let’s move together! Stay close!",
    "speaker": "Caleb Wright"
  },
  {
    "uid": "a9739084-b356-4be5-ad63-66e0c7dd607c",
    "time": 25.6666431,
    "location": {
      "x": -43.1689224,
      "y": 0.0101999044,
      "z": -51.6836777
    },
    "content": "Let me walk you through the assignment. It’s easier if we break it down into smaller parts.",
    "speaker": "Amelia Chen"
  },
  {
    "uid": "40c304c2-5d6d-4265-a8cd-030d7f87187d",
    "time": 25.71008,
    "location": {
      "x": -3.56733418,
      "y": 0.0202000141,
      "z": -39.0838623
    },
    "content": "Harper, Amelia, let's go with the others! We need to get out of here!",
    "speaker": "Scarlett Kim"
  },
  {
    "uid": "8319401d-255c-4cc7-ae4d-9b21857bd3aa",
    "time": 26.1146526,
    "location": {
      "x": -52.06823,
      "y": 0.0101999044,
      "z": -38.4664421
    },
    "content": "Everyone, stay calm and take cover. Don’t move.",
    "speaker": "Robert Chen"
  },
  {
    "uid": "c36fc18e-c056-4ee6-8bd1-24665bf9e148",
    "time": 26.18054,
    "location": {
      "x": -66.10562,
      "y": 0.0202000141,
      "z": -51.6225777
    },
    "content": "Everyone, stay down and be quiet. We need to hide.",
    "speaker": "Noah Martinez"
  },
  {
    "uid": "6b6bbe9f-7117-4bac-8080-09a9ba2c5210",
    "time": 26.1950817,
    "location": {
      "x": -12.204361,
      "y": 0.0101999044,
      "z": -25.45644
    },
    "content": "Harper, we need to get out of here. Follow me to the kitchen yard.",
    "speaker": "Aiden Thompson"
  },
  {
    "uid": "a3e3f083-8582-46d8-9595-8a22c4217ab9",
    "time": 26.2240734,
    "location": {
      "x": -54.4398956,
      "y": 0.0101999044,
      "z": -51.66615
    },
    "content": "¡Vamos, chicos! We need to get out of here now!",
    "speaker": "Karen Martinez"
  },
  {
    "uid": "0224fd8e-039b-47c9-ae51-e01b7bfff0c8",
    "time": 26.4111023,
    "location": {
      "x": -30.7342625,
      "y": 0.0101999044,
      "z": -43.2603149
    },
    "content": "Mila, stay down and take cover with me.",
    "speaker": "Margaret Wilson"
  },
  {
    "uid": "f85b2a71-edf1-442c-a73c-13a7579587c3",
    "time": 26.4111023,
    "location": {
      "x": -10.9477806,
      "y": 0.0101999044,
      "z": -40.9449463
    },
    "content": "Everyone, stay down and quiet. We need to hide.",
    "speaker": "Victoria Wright"
  },
  {
    "uid": "520eee7c-20ae-433c-9375-8fe38dd4bd2a",
    "time": 26.6470337,
    "location": {
      "x": -54.4589767,
      "y": 0.0101999044,
      "z": -52.2658424
    },
    "content": "Karen, Jason, get down! We need to hide right now.",
    "speaker": "Mason Scott"
  },
  {
    "uid": "b2b50856-927a-4cdb-bb85-519c676609aa",
    "time": 26.7074089,
    "location": {
      "x": -43.44899,
      "y": 0.0101999044,
      "z": -52.3915367
    },
    "content": "What’s happening? Where is everyone going?",
    "speaker": "Mia Rodriguez"
  },
  {
    "uid": "a4024e83-5c3c-4791-b9d3-2d001305cd20",
    "time": 26.7365036,
    "location": {
      "x": -52.88533,
      "y": 0.0101999044,
      "z": -37.77618
    },
    "content": "Lisa, Ethan, don’t forget we’ve got a fresh batch of veggie wraps today—perfect fuel for your afternoon classes!",
    "speaker": "Gloria Washington"
  },
  {
    "uid": "2f51aed6-6816-44ae-bf13-b356903161d8",
    "time": 27.158535,
    "location": {
      "x": -65.3937149,
      "y": 0.0101999044,
      "z": -52.23289
    },
    "content": "Everyone, stay calm! We need to be ready to act if the shooter comes here.",
    "speaker": "Elizabeth Wilson"
  },
  {
    "uid": "43b26e6a-e61c-487d-8e8c-e3ea9a9afbef",
    "time": 27.2807217,
    "location": {
      "x": -31.4388847,
      "y": 0.0101999044,
      "z": -52.32778
    },
    "content": "Everyone, stay quiet and get to the closest hiding spot. We can’t risk moving too much.",
    "speaker": "William Davis"
  },
  {
    "uid": "e8d17c32-695f-4851-9fba-dc9e8e1ddd93",
    "time": 27.342411,
    "location": {
      "x": -31.7430725,
      "y": 0.0151999,
      "z": -25.0809135
    },
    "content": "Benjamin, we need to go! There’s a shooter!",
    "speaker": "Charlotte Davis"
  },
  {
    "uid": "102833d8-c262-4786-b3c5-0445fc094cb4",
    "time": 27.342411,
    "location": {
      "x": -63.10183,
      "y": 0.0101999044,
      "z": -44.0321
    },
    "content": "Everyone, stay quiet and take cover!",
    "speaker": "Sophia Anderson"
  },
  {
    "uid": "027b32ed-9169-43af-b2dd-4de97b080d0c",
    "time": 27.4636631,
    "location": {
      "x": -14.011981,
      "y": 0.0202000141,
      "z": -28.3122711
    },
    "content": "Jordan, we need to get out of here now! Follow me!",
    "speaker": "Diane Jackson"
  },
  {
    "uid": "9ce689f6-6684-4829-a203-04274777da6d",
    "time": 27.49192,
    "location": {
      "x": -31.8164253,
      "y": 0.0101999044,
      "z": -25.5249062
    },
    "content": "Charlotte, we need to go! There’s a shooter—head to the outside_courtyard!",
    "speaker": "Benjamin Scott"
  },
  {
    "uid": "c3d2f424-084c-4bb6-bd17-8b6f88227225",
    "time": 27.9613857,
    "location": {
      "x": -56.8389969,
      "y": 0.0101999044,
      "z": -53.118
    },
    "content": "Guys, get down! I heard a gunshot. Stay quiet and don’t move.",
    "speaker": "Jason Miller"
  },
  {
    "uid": "895827ce-8d7d-4406-a737-57ea26c34f0c",
    "time": 28.3121815,
    "location": {
      "x": -4.890902,
      "y": 0.0151999,
      "z": -30.4592686
    },
    "content": "Everyone, get down! There's a shooter!",
    "speaker": "Henry Johnson"
  },
  {
    "uid": "b9b11926-792e-4f8b-82b0-6ebd24e9a649",
    "time": 28.4496975,
    "location": {
      "x": -63.8661728,
      "y": 0.0101999044,
      "z": -36.91638
    },
    "content": "Guys, let’s stick together and get out of here! Follow me!",
    "speaker": "Ava Martinez"
  },
  {
    "uid": "513688e1-3779-4f17-aef7-cf1a5611678c",
    "time": 28.4496975,
    "location": {
      "x": -38.9524231,
      "y": 0.0101999044,
      "z": -47.3384
    },
    "content": "Oh no, that was a gunshot! Let’s get out of here!",
    "speaker": "Emily Zhang"
  },
  {
    "uid": "da53397b-f73b-4340-9917-23f552b83f4b",
    "time": 28.5485878,
    "location": {
      "x": -32.9372368,
      "y": 0.0101999044,
      "z": -49.465416
    },
    "content": "Where are we going? Should we follow them?",
    "speaker": "Alexander Lee"
  },
  {
    "uid": "828dd242-0936-4df5-9e7a-6f2c8e16fd3b",
    "time": 29.0154915,
    "location": {
      "x": -8.088129,
      "y": 0.0101999044,
      "z": -51.52864
    },
    "content": "Olivia, let’s stick together and follow the others!",
    "speaker": "Sebastian Garcia"
  },
  {
    "uid": "f17547ef-d1de-451e-b1db-9c7b508c59f4",
    "time": 29.90276,
    "location": {
      "x": -25.7609425,
      "y": 0.0101999044,
      "z": -29.3267879
    },
    "content": "Walter, stay quiet. We need to stay hidden.",
    "speaker": "Zoe Miller"
  },
  {
    "uid": "23415516-cc92-43c6-82d6-c1bc52bdd96a",
    "time": 29.955761,
    "location": {
      "x": -6.02069473,
      "y": 0.0101999044,
      "z": -37.90731
    },
    "content": "Let's go to the hallway, everyone! Stay together!",
    "speaker": "Zainab Malik"
  },
  {
    "uid": "6c9af65c-cd49-44f6-a45a-44c43105078f",
    "time": 30.4152565,
    "location": {
      "x": -8.012004,
      "y": 0.0101999044,
      "z": -40.7094078
    },
    "content": "Everyone, stay together! Let's move as a group!",
    "speaker": "Noah Johnson"
  },
  {
    "uid": "9410fe16-e7c4-4552-b7a5-a615435532ea",
    "time": 30.42969,
    "location": {
      "x": -18.3698883,
      "y": 0.0151999,
      "z": -23.3171616
    },
    "content": "Let's keep moving towards hallway2! Stay close and don't get separated!",
    "speaker": "James Rodriguez"
  },
  {
    "uid": "47d23bb4-b428-488f-bbbb-6e6cbc98fa44",
    "time": 31.2061024,
    "location": {
      "x": -19.0284023,
      "y": 0.0101999044,
      "z": -38.4066467
    },
    "content": "Lily, let’s go to hallway2! Stay close!",
    "speaker": "Harper Garcia"
  },
  {
    "uid": "8458d74f-db20-45b1-af50-a7c0162948d2",
    "time": 31.5972652,
    "location": {
      "x": -12.1951132,
      "y": 0.0101999044,
      "z": -26.1000023
    },
    "content": "Everyone, stay together and move quickly!",
    "speaker": "Robert Chen"
  },
  {
    "uid": "68dbc488-707f-422b-99f7-4b62e44d2d74",
    "time": 32.2631035,
    "location": {
      "x": -25.1670818,
      "y": 0.0101999044,
      "z": -29.2411919
    },
    "content": "Zoe, stay down and hide. There’s a shooter nearby.",
    "speaker": "Walter Thompson"
  },
  {
    "uid": "8f8e6190-4f73-432d-952a-20ede04fad26",
    "time": 32.5878334,
    "location": {
      "x": -64.84151,
      "y": 0.0101999044,
      "z": -36.71119
    },
    "content": "Guys, let’s stick together and get out of here! Follow me!",
    "speaker": "Matthew Brown"
  },
  {
    "uid": "b9f9f178-4acf-4108-a6f5-95b10ea96859",
    "time": 32.6024437,
    "location": {
      "x": -44.11653,
      "y": 0.0101999044,
      "z": -51.56311
    },
    "content": "Mia, Amelia, we need to get out of here now! Follow me!",
    "speaker": "Natalie Chen"
  },
  {
    "uid": "77ed9898-7dd3-4dae-83f6-da8864b01e6d",
    "time": 32.6024437,
    "location": {
      "x": -8.723,
      "y": 0.0101999044,
      "z": -28.883
    },
    "content": "Lucas, we need to go! Follow me to the kitchen yard!",
    "speaker": "Emma Taylor"
  },
  {
    "uid": "b6f3d45e-5d4d-4deb-890e-4e3f840bf2e0",
    "time": 33.06294,
    "location": {
      "x": -63.2596741,
      "y": 0.0101999044,
      "z": -36.80984
    },
    "content": "Everyone, stay calm. If the shooter comes here, I’ll try to stop them. Just be ready to run if I say so.",
    "speaker": "Elijah Thompson"
  },
  {
    "uid": "b2505fb0-43d1-48bc-8d23-ec524237d57d",
    "time": 33.64992,
    "location": {
      "x": -10.5549192,
      "y": 0.0101999044,
      "z": -40.5219841
    },
    "content": "Everyone, stay calm and follow Victoria’s instructions. I’ll handle this.",
    "speaker": "Jackson Lee"
  },
  {
    "uid": "53e2a29a-1516-44b5-bdf3-03f4a54a4670",
    "time": 34.27603,
    "location": {
      "x": -32.8409081,
      "y": 0.0101999044,
      "z": -52.93132
    },
    "content": "Mila, stay down and don’t make a sound. We’ll be okay if we stay hidden.",
    "speaker": "William Davis"
  },
  {
    "uid": "58cf3ffb-d452-4d12-8d71-79c94de826a3",
    "time": 34.6274223,
    "location": {
      "x": -77.62546,
      "y": 0.0101999044,
      "z": -43.2385521
    },
    "content": "Abigail, we need to move, but quietly. Let’s find somewhere safe.",
    "speaker": "Zoe Patel"
  },
  {
    "uid": "ad64c498-1fdb-4db2-923d-35b50f7e1ddc",
    "time": 34.73066,
    "location": {
      "x": -32.7550926,
      "y": 0.0101999044,
      "z": -51.7404861
    },
    "content": "Everyone, stay quiet and take cover. We need to hide.",
    "speaker": "Mila Patel"
  },
  {
    "uid": "abbd8b29-bc8d-415b-98f3-a3f1f884a856",
    "time": 34.7457657,
    "location": {
      "x": -49.44702,
      "y": 0.0101999044,
      "z": -47.640934
    },
    "content": "Sophia, it’s safer to stay here for now. We’ll reassess when it’s clear.",
    "speaker": "Marcus Johnson"
  },
  {
    "uid": "2fdafd76-af1c-43b2-94f6-662228f9120d",
    "time": 35.0565567,
    "location": {
      "x": -64.09072,
      "y": 0.0101999044,
      "z": -37.77232
    },
    "content": "Everyone, stay down and be quiet. We need to hide.",
    "speaker": "Evelyn Martinez"
  },
  {
    "uid": "b331a39f-e72a-419c-b2fa-1f30238c551d",
    "time": 35.20505,
    "location": {
      "x": -72.40515,
      "y": 0.0151999,
      "z": -42.35075
    },
    "content": "Stay low and don't make any noise. We need to stay hidden.",
    "speaker": "Frank Ramirez"
  },
  {
    "uid": "d46459cc-9ea8-4ddf-a829-0daf8a1a2129",
    "time": 35.265007,
    "location": {
      "x": -52.63842,
      "y": 0.0101999044,
      "z": -37.1391945
    },
    "content": "Everyone, stay calm! We need to move to a safe spot—follow me!",
    "speaker": "Lisa Patel"
  },
  {
    "uid": "b69bb431-aabb-40f6-936d-efd9ceda0584",
    "time": 35.376976,
    "location": {
      "x": -4.465849,
      "y": 0.0101999044,
      "z": -32.97972
    },
    "content": "Stay quiet and don't move. We need to stay hidden.",
    "speaker": "Benjamin Moore"
  },
  {
    "uid": "40a4fe0a-46bc-4ad8-a928-cc30b79cb03c",
    "time": 35.4514046,
    "location": {
      "x": -4.41413164,
      "y": 0.0101999044,
      "z": -37.98287
    },
    "content": "Where are we going? Should we follow everyone?",
    "speaker": "Madison Lee"
  },
  {
    "uid": "ddcc77b8-3465-4b59-b5d0-6c257567d040",
    "time": 35.70082,
    "location": {
      "x": -75.70301,
      "y": 0.0101999044,
      "z": -36.48232
    },
    "content": "Stay quiet and don’t move. We’ll be safe if we stay hidden.",
    "speaker": "Helen Martinez"
  },
  {
    "uid": "985cf322-490a-4304-a8ed-0397cb7a466e",
    "time": 35.957283,
    "location": {
      "x": -66.10562,
      "y": 0.0202000141,
      "z": -51.6225777
    },
    "content": "Elizabeth, stay low and don't make any noise.",
    "speaker": "Noah Martinez"
  },
  {
    "uid": "cb9c20de-2750-4c79-8038-4a551e2b4086",
    "time": 38.8667641,
    "location": {
      "x": -64.09783,
      "y": 0.0101999044,
      "z": -36.362915
    },
    "content": "Ava’s right, let’s move to the hallway, but stay close and be ready to act if we encounter the shooter.",
    "speaker": "Sarah Johnson"
  },
  {
    "uid": "e16e7f1e-7dfd-4a2e-bc5e-498e7be6492f",
    "time": 39.1404266,
    "location": {
      "x": -65.3937149,
      "y": 0.0101999044,
      "z": -52.23289
    },
    "content": "Noah, stay close to me. If the shooter comes here, we need to be ready to fight back.",
    "speaker": "Elizabeth Wilson"
  },
  {
    "uid": "961a3c62-e5db-40d3-95df-f9596f2b15fd",
    "time": 39.5743141,
    "location": {
      "x": -52.8890839,
      "y": 0.0101999044,
      "z": -35.99283
    },
    "content": "Guys, seriously, stop talking! We need to stay hidden and quiet until it’s safe.",
    "speaker": "Ethan Brown"
  },
  {
    "uid": "4f362f0c-508b-451f-b77d-d559fc57ca35",
    "time": 40.6081963,
    "location": {
      "x": -17.0500011,
      "y": 0.0101999044,
      "z": -40.92456
    },
    "content": "Harper, stay down and don’t move!",
    "speaker": "Lily Kim"
  },
  {
    "uid": "c507195c-bb34-4f16-9cef-001e65c93c3e",
    "time": 40.809063,
    "location": {
      "x": -11.0224037,
      "y": 0.0101999044,
      "z": -30.3448982
    },
    "content": "Emma, we need to go! Follow the others!",
    "speaker": "Lucas Garcia"
  },
  {
    "uid": "fb0c72c5-9481-4629-8fee-a06ed0f11df9",
    "time": 41.5294266,
    "location": {
      "x": 8.489259,
      "y": 0.0101999044,
      "z": -48.3175621
    },
    "content": "Olivia, let’s go! The exit is just ahead!",
    "speaker": "Sebastian Garcia"
  },
  {
    "uid": "eb53dbd9-b398-4f1d-9c00-422ee7e3f3b4",
    "time": 41.59306,
    "location": {
      "x": -69.853096,
      "y": 0.0151999,
      "z": -42.6816521
    },
    "content": "Let’s go to hallway1! Everyone’s heading that way!",
    "speaker": "Sophia Garcia"
  },
  {
    "uid": "1ba9faf1-f1fa-438b-a1f2-02de22c6ec2c",
    "time": 41.8951836,
    "location": {
      "x": -18.3296089,
      "y": 0.0101999044,
      "z": -40.44598
    },
    "content": "Harper, Lily, wait for me! I’m coming with you!",
    "speaker": "Scarlett Kim"
  },
  {
    "uid": "a1132449-f6e0-41dd-b603-74094918e03a",
    "time": 42.2585831,
    "location": {
      "x": -63.10183,
      "y": 0.0101999044,
      "z": -44.0321
    },
    "content": "Stay quiet and don’t move. We need to stay hidden.",
    "speaker": "Sophia Anderson"
  },
  {
    "uid": "de279cbf-687c-42d3-9045-c0c753991caf",
    "time": 42.3292961,
    "location": {
      "x": -54.4589767,
      "y": 0.0101999044,
      "z": -52.2658424
    },
    "content": "Jason, stay down and don’t make any noise. We’ll be okay if we stay hidden.",
    "speaker": "Mason Scott"
  },
  {
    "uid": "f24f2d17-e52b-4265-9e45-91633f4dda76",
    "time": 42.3557243,
    "location": {
      "x": -58.5552444,
      "y": 0.0101999044,
      "z": -42.913826
    },
    "content": "Wait for me! I’m coming too!",
    "speaker": "Mia Rodriguez"
  },
  {
    "uid": "24553b44-54ab-4fd4-b93d-2b01a131c826",
    "time": 42.4775963,
    "location": {
      "x": -53.2103348,
      "y": 0.0101999044,
      "z": -37.3045654
    },
    "content": "Everyone, stay quiet and take cover. We need to hide until it’s safe.",
    "speaker": "Alex Rivera"
  },
  {
    "uid": "fbc3f276-c31f-43a4-93ae-f9f4129d863f",
    "time": 42.61301,
    "location": {
      "x": -38.11171,
      "y": 0.0101999044,
      "z": -43.3135452
    },
    "content": "Let's move to the hallway, everyone! Stay together!",
    "speaker": "Emma Rodriguez"
  },
  {
    "uid": "4c039730-0bce-4401-a0e3-35a9e3563a02",
    "time": 42.6579781,
    "location": {
      "x": -52.8838654,
      "y": 0.0101999044,
      "z": -37.94044
    },
    "content": "Everyone, stay together and follow Robert! We need to move quickly!",
    "speaker": "Gloria Washington"
  },
  {
    "uid": "9498805d-0cd5-4448-ac53-af4bab309fe4",
    "time": 42.7085876,
    "location": {
      "x": -56.8389969,
      "y": 0.0101999044,
      "z": -53.118
    },
    "content": "Mason, stay down and don’t make any noise. We’ll be okay if we stay hidden.",
    "speaker": "Jason Miller"
  },
  {
    "uid": "b2cd3523-75da-46e1-b67a-8c5e2f631b04",
    "time": 42.7573776,
    "location": {
      "x": -63.2871933,
      "y": 0.0101999044,
      "z": -42.8098335
    },
    "content": "Alexander, we need to stop the shooter! Follow me!",
    "speaker": "Audrey Thompson"
  },
  {
    "uid": "2c3ab71e-c3e8-4a42-98e2-17db76ab75b7",
    "time": 42.8523674,
    "location": {
      "x": -25.1670818,
      "y": 0.0101999044,
      "z": -29.2411919
    },
    "content": "Stay quiet, Zoe. We need to remain hidden.",
    "speaker": "Walter Thompson"
  },
  {
    "uid": "0c32e35e-d880-45c4-8076-e7b69d82b950",
    "time": 42.8998,
    "location": {
      "x": -30.7342625,
      "y": 0.0101999044,
      "z": -43.2603149
    },
    "content": "Aiden, stay quiet and don’t move. We need to stay hidden.",
    "speaker": "Margaret Wilson"
  },
  {
    "uid": "268d5f6f-b701-4bdb-ad17-3e84eb804e2f",
    "time": 42.9249,
    "location": {
      "x": -53.1774139,
      "y": 0.0101999044,
      "z": -36.5190048
    },
    "content": "Everyone, stay calm and follow Robert’s lead. We need to act together if the shooter comes this way.",
    "speaker": "Chloe Wilson"
  },
  {
    "uid": "85462a72-f906-4caa-9b1c-d04bc6ef9fc4",
    "time": 43.28529,
    "location": {
      "x": -42.9244,
      "y": 0.0101999044,
      "z": -51.4295464
    },
    "content": "Natalie, Mia, we need to run! Follow me!",
    "speaker": "Amelia Chen"
  },
  {
    "uid": "b9adc837-e4bc-4bae-bd12-bad2332c840f",
    "time": 43.4614944,
    "location": {
      "x": -25.7609425,
      "y": 0.0101999044,
      "z": -29.3267879
    },
    "content": "Walter, we need to stay down and stay quiet. Don’t move.",
    "speaker": "Zoe Miller"
  },
  {
    "uid": "f3700bb6-97bb-450d-9565-a9f09e72e117",
    "time": 43.7104073,
    "location": {
      "x": -51.655983,
      "y": 0.0101999044,
      "z": -42.9128838
    },
    "content": "Stay close, everyone! Follow the group to the far_right_yard!",
    "speaker": "David Thompson"
  },
  {
    "uid": "bc80512c-c063-4dec-a976-40fc79fec846",
    "time": 44.0521965,
    "location": {
      "x": -10.5294657,
      "y": 0.0101999044,
      "z": -40.5680656
    },
    "content": "Victoria, I’m with you—where are we heading? Let’s stick together!",
    "speaker": "Ethan Wilson"
  },
  {
    "uid": "8d891282-d0af-44ce-92a7-14870e303ea1",
    "time": 44.98804,
    "location": {
      "x": -51.7269974,
      "y": 0.0101999044,
      "z": -38.9302826
    },
    "content": "Stay quiet and don’t move. We’re safer here for now.",
    "speaker": "Robert Chen"
  },
  {
    "uid": "5e2d213c-822f-4052-be4f-176f974275bf",
    "time": 45.01444,
    "location": {
      "x": -32.7550926,
      "y": 0.0101999044,
      "z": -51.7404861
    },
    "content": "William, let’s move to that hide spot over there. It’s closer and safer.",
    "speaker": "Mila Patel"
  },
  {
    "uid": "edf4030b-bf26-45e0-8b92-7a961a915dbc",
    "time": 45.16559,
    "location": {
      "x": -49.44702,
      "y": 0.0101999044,
      "z": -47.640934
    },
    "content": "Stay quiet and stay close. We’re safe here for now.",
    "speaker": "Marcus Johnson"
  },
  {
    "uid": "d8d7d8e4-1017-4c47-ab7f-efc1968ebfd9",
    "time": 45.2229958,
    "location": {
      "x": -10.92807,
      "y": 0.0101999044,
      "z": -40.5996666
    },
    "content": "Stay down and stay safe! I’m going to confront the shooter.",
    "speaker": "Jackson Lee"
  },
  {
    "uid": "f7cb2eaa-2935-4859-8e9d-ae824294042c",
    "time": 45.33578,
    "location": {
      "x": -48.1969452,
      "y": 0.0101999044,
      "z": -42.41202
    },
    "content": "Emma, wait for me! Let’s stay together!",
    "speaker": "Alexander Lee"
  },
  {
    "uid": "16420de7-4192-4b47-9146-b0a02ce7c85c",
    "time": 45.487545,
    "location": {
      "x": -39.35962,
      "y": 0.0101999044,
      "z": -42.5701828
    },
    "content": "Let’s find a place to hide, quickly and quietly.",
    "speaker": "Karen Martinez"
  },
  {
    "uid": "3c29c811-b854-4bdc-abd1-1e03693344f4",
    "time": 45.53737,
    "location": {
      "x": -75.5494461,
      "y": 0.0101999044,
      "z": -44.23245
    },
    "content": "Sophia, let’s go! Stay close to me!",
    "speaker": "Ava Martinez"
  },
  {
    "uid": "21c70385-2d2c-489d-9045-12fb1b9648f6",
    "time": 45.6325035,
    "location": {
      "x": -72.47842,
      "y": 0.0151999,
      "z": -42.3653069
    },
    "content": "Stay calm and don't move. We need to wait this out.",
    "speaker": "Frank Ramirez"
  },
  {
    "uid": "0dcbf79d-eddf-4d86-840b-175b64c1698c",
    "time": 46.2691879,
    "location": {
      "x": -66.0766,
      "y": 0.0101999044,
      "z": -51.6267281
    },
    "content": "Noah, let's stay near the door. If the shooter comes in, we’ll have a better chance to act.",
    "speaker": "Elizabeth Wilson"
  },
  {
    "uid": "c10f4f38-4a48-4339-a70d-c1a16f4b9bd9",
    "time": 46.3782425,
    "location": {
      "x": -75.70301,
      "y": 0.0101999044,
      "z": -36.48232
    },
    "content": "Stay calm and stay down. We’re safer here as long as we stay hidden.",
    "speaker": "Helen Martinez"
  },
  {
    "uid": "4da48e9e-bf6e-4c91-aa7a-44c370d0e99d",
    "time": 46.7882767,
    "location": {
      "x": -64.38872,
      "y": 0.0101999044,
      "z": -38.2871666
    },
    "content": "I think we should stay here. Moving might make us more visible.",
    "speaker": "Evelyn Martinez"
  },
  {
    "uid": "73cc8f9f-8409-40a3-a1e1-7a70d5947297",
    "time": 47.20113,
    "location": {
      "x": -75.79459,
      "y": 0.0101999044,
      "z": -43.3299332
    },
    "content": "Mia, let’s go! We need to get out of here!",
    "speaker": "Emily Zhang"
  },
  {
    "uid": "dade2e5c-4d55-4035-91b0-661a01da62db",
    "time": 47.45361,
    "location": {
      "x": -29.4903183,
      "y": 0.0101999044,
      "z": -43.0047722
    },
    "content": "Aiden, Margaret, let’s go to the far_right_yard! We need to get out of here!",
    "speaker": "Harper Garcia"
  },
  {
    "uid": "cc49105f-4c4b-4a40-a15d-2fc3b64fda7b",
    "time": 47.45361,
    "location": {
      "x": -63.2596741,
      "y": 0.0101999044,
      "z": -36.80984
    },
    "content": "Stay low and quiet. If they come in, I’ll handle it. Be ready to move if I give the signal.",
    "speaker": "Elijah Thompson"
  },
  {
    "uid": "f96121e9-b901-47c5-a06c-f4d81f6e43d6",
    "time": 47.5949059,
    "location": {
      "x": -67.11081,
      "y": 0.0202000141,
      "z": -51.39391
    },
    "content": "We can't fight back now. Stay hidden and stay quiet.",
    "speaker": "Noah Martinez"
  },
  {
    "uid": "ece6a661-22ba-4a0f-80f1-17fb8adfdd21",
    "time": 48.4413338,
    "location": {
      "x": -32.8141251,
      "y": 0.0101999044,
      "z": -53.09363
    },
    "content": "Mila, just breathe. We’re going to get through this. Stay still and stay quiet.",
    "speaker": "William Davis"
  },
  {
    "uid": "af7f714c-4c35-4c9e-94c1-2fa1eb9d4673",
    "time": 48.4629021,
    "location": {
      "x": -67.43721,
      "y": 0.0101999044,
      "z": -43.1843643
    },
    "content": "David, we need to get to the far_right_yard. It's the safest way out!",
    "speaker": "Natalie Chen"
  },
  {
    "uid": "28a095a2-597d-4289-b375-0ed86723b31c",
    "time": 49.95139,
    "location": {
      "x": -103.671288,
      "y": 0.0101999044,
      "z": -45.9364624
    },
    "content": "Mateo, let’s head to the exit. We’re almost there.",
    "speaker": "Zoe Patel"
  },
  {
    "uid": "85f93481-f20f-4116-ad72-c8b2a506a453",
    "time": 49.98758,
    "location": {
      "x": -64.33698,
      "y": 0.0101999044,
      "z": -44.3495026
    },
    "content": "Elijah, Evelyn, let’s go! We need to get out of here!",
    "speaker": "Matthew Brown"
  },
  {
    "uid": "2f3018f4-9831-4767-ba94-71ea16d9d771",
    "time": 50.7346649,
    "location": {
      "x": -26.77593,
      "y": 0.0101999044,
      "z": -43.865242
    },
    "content": "Karen, Emma, let’s find a place to hide—stay quiet and follow me.",
    "speaker": "Lisa Patel"
  },
  {
    "uid": "aa5e818e-1246-45ff-8927-e659a7314920",
    "time": 52.503727,
    "location": {
      "x": -63.10183,
      "y": 0.0101999044,
      "z": -44.0321
    },
    "content": "Stay down and stay quiet. We’ll get through this together.",
    "speaker": "Sophia Anderson"
  },
  {
    "uid": "1c19683b-d996-4bad-ad24-409e78486db7",
    "time": 53.22055,
    "location": {
      "x": -54.4589767,
      "y": 0.0101999044,
      "z": -52.2658424
    },
    "content": "Jason, don’t move. We’ll get through this if we stay hidden.",
    "speaker": "Mason Scott"
  },
  {
    "uid": "89e6a593-b720-4b8c-985a-a9f54f66bf55",
    "time": 53.9068871,
    "location": {
      "x": -52.8890839,
      "y": 0.0101999044,
      "z": -35.99283
    },
    "content": "Guys, I think we should stay here. Moving might make things worse.",
    "speaker": "Ethan Brown"
  },
  {
    "uid": "66bcd45d-d63b-4fc7-baf9-d3450308aca7",
    "time": 53.95365,
    "location": {
      "x": -79.2283249,
      "y": 0.0101999044,
      "z": -43.9728966
    },
    "content": "Abigail, let’s head to the far_right_yard. It’s the closest exit, and we need to get out of here quickly.",
    "speaker": "Sarah Johnson"
  },
  {
    "uid": "ede4e4ae-e1fb-46b3-98a6-339a277cba6a",
    "time": 54.1103363,
    "location": {
      "x": -32.9283371,
      "y": 0.0101999044,
      "z": -52.5045853
    },
    "content": "William, stay quiet and don’t move. We’ll be safer here.",
    "speaker": "Mila Patel"
  },
  {
    "uid": "9b6a1fc8-065a-42c3-b560-bab17dff84bf",
    "time": 55.2872353,
    "location": {
      "x": -72.66551,
      "y": 0.0101999044,
      "z": -44.1147423
    },
    "content": "Let’s keep moving! We need to get out of here!",
    "speaker": "Ava Martinez"
  },
  {
    "uid": "74086bd2-76ee-4c22-a30a-5d670f145006",
    "time": 55.8722,
    "location": {
      "x": -66.6621246,
      "y": 0.0101999044,
      "z": -51.495842
    },
    "content": "Noah, the shooter is getting closer. Stay behind me and be ready to act if they come in.",
    "speaker": "Elizabeth Wilson"
  },
  {
    "uid": "7bf45de9-a516-47ad-89e2-14cc3407823c",
    "time": 55.97478,
    "location": {
      "x": -53.20706,
      "y": 0.0101999044,
      "z": -37.30542
    },
    "content": "Robert, Ethan, stay low and don’t make any noise. We’ll get through this.",
    "speaker": "Alex Rivera"
  },
  {
    "uid": "62dab2f6-7463-45a1-b433-7d0350b799ab",
    "time": 56.1702843,
    "location": {
      "x": -56.8389969,
      "y": 0.0101999044,
      "z": -53.118
    },
    "content": "Mason, don’t panic. Just stay down and stay quiet. We’ll get through this.",
    "speaker": "Jason Miller"
  },
  {
    "uid": "f4dfcdd1-398f-481b-9d67-fa896f69d16b",
    "time": 56.3186874,
    "location": {
      "x": -51.7269974,
      "y": 0.0101999044,
      "z": -38.9302826
    },
    "content": "Alex, stay quiet and don’t move. We’re safer here.",
    "speaker": "Robert Chen"
  },
  {
    "uid": "77dacd06-69bf-41b5-99c2-f4c5751bbb18",
    "time": 57.11851,
    "location": {
      "x": -30.7342625,
      "y": 0.0101999044,
      "z": -43.2603149
    },
    "content": "Harper, Jordan, stay down and don’t move. It’s too risky to go anywhere right now.",
    "speaker": "Margaret Wilson"
  },
  {
    "uid": "56086c5a-e90c-45ac-afda-4e201ea5a6bf",
    "time": 57.5435143,
    "location": {
      "x": -51.4326477,
      "y": 0.0101999044,
      "z": -44.0571175
    },
    "content": "Mia, where are you going? Can I come with you?",
    "speaker": "Scarlett Kim"
  },
  {
    "uid": "9275ae9e-c7b6-4e87-ba83-e167a88012ee",
    "time": 58.06984,
    "location": {
      "x": -26.4885616,
      "y": 0.0101999044,
      "z": -44.43851
    },
    "content": "Jordan, wait! I’m coming with you!",
    "speaker": "Mia Rodriguez"
  },
  {
    "uid": "d788d428-698c-4b57-a7ff-87c59d20862e",
    "time": 58.2891846,
    "location": {
      "x": -64.53026,
      "y": 0.0101999044,
      "z": -43.4347649
    },
    "content": "Let's keep moving to hallway1, everyone! Stay close!",
    "speaker": "Emma Rodriguez"
  },
  {
    "uid": "29d612f3-20f4-4ab0-83fa-d6046e0ae039",
    "time": 58.67206,
    "location": {
      "x": -32.8141251,
      "y": 0.0101999044,
      "z": -53.09363
    },
    "content": "Mila, we’re doing the right thing by staying here. Just keep breathing and stay quiet.",
    "speaker": "William Davis"
  },
  {
    "uid": "3154992c-be1f-43ed-a255-cf4acf4b85fc",
    "time": 58.7079659,
    "location": {
      "x": -72.47842,
      "y": 0.0151999,
      "z": -42.3653069
    },
    "content": "Keep quiet and stay down. We’ll get through this if we stay hidden.",
    "speaker": "Frank Ramirez"
  },
  {
    "uid": "2ec75d7e-9e42-4005-ba94-4a24b29cd6ca",
    "time": 58.7351646,
    "location": {
      "x": -49.44702,
      "y": 0.0101999044,
      "z": -47.640934
    },
    "content": "Stay low and quiet. We’re doing the right thing by staying here.",
    "speaker": "Marcus Johnson"
  },
  {
    "uid": "432837df-3b87-4dde-98cc-af364ababb64",
    "time": 59.0356522,
    "location": {
      "x": -67.42448,
      "y": 0.0101999044,
      "z": -51.3507767
    },
    "content": "Elizabeth, stay close and keep quiet. We’ll be okay if we stay hidden.",
    "speaker": "Noah Martinez"
  },
  {
    "uid": "b7639a1e-6d7a-476b-8508-994daaeb5e72",
    "time": 59.2519951,
    "location": {
      "x": -75.70301,
      "y": 0.0101999044,
      "z": -36.48232
    },
    "content": "Lucas, stay close and don’t make any noise. We’ll get through this together.",
    "speaker": "Helen Martinez"
  },
  {
    "uid": "0da0e332-99df-493c-868b-2569b6112636",
    "time": 59.563736,
    "location": {
      "x": -64.38872,
      "y": 0.0101999044,
      "z": -38.2871666
    },
    "content": "Elijah, we’ll be safer if we stay here. Let’s just stay quiet and wait for help.",
    "speaker": "Evelyn Martinez"
  },
  {
    "uid": "ca25b0da-1473-48f4-a173-c7e079ce262d",
    "time": 59.9317322,
    "location": {
      "x": -95.20374,
      "y": 0.0101999044,
      "z": -43.887
    },
    "content": "Abigail, Natalie, Sarah, stay with me! We're going to the far_right_yard!",
    "speaker": "David Thompson"
  }
]